CHANGES
INSTALL
README
bb_example.py
bb_shell.py
bitbucket.py
bitbucket_example.cfg
setup.py
test_filter.py
BitBucket.egg-info/PKG-INFO
BitBucket.egg-info/SOURCES.txt
BitBucket.egg-info/top_level.txt
s3amazon/README
s3amazon/S3.py
s3amazon/__init__.py
s3amazon/s3-driver.py
s3amazon/s3-test.py
