Metadata-Version: 1.0
Name: BitBucket
Version: 0.3d
Summary: Module for accessing Amazon S3
Home-page: http://other10percent.com/?cat=9
Author: Mitch Garnaat
Author-email: mitch@garnaat.org
License: UNKNOWN
Keywords: web services amazon s3
Platform: UNKNOWN
